LICENSE
MANIFEST.in
README.rst
setup.py
src/pvc-tui
src/pvc/__init__.py
src/pvc/core.py
src/pvc.egg-info/PKG-INFO
src/pvc.egg-info/SOURCES.txt
src/pvc.egg-info/dependency_links.txt
src/pvc.egg-info/requires.txt
src/pvc.egg-info/top_level.txt
src/pvc/widget/__init__.py
src/pvc/widget/administration.py
src/pvc/widget/alarm.py
src/pvc/widget/checklist.py
src/pvc/widget/cluster.py
src/pvc/widget/common.py
src/pvc/widget/datacenter.py
src/pvc/widget/datastore.py
src/pvc/widget/debug.py
src/pvc/widget/device.py
src/pvc/widget/event.py
src/pvc/widget/form.py
src/pvc/widget/gauge.py
src/pvc/widget/home.py
src/pvc/widget/hostsystem.py
src/pvc/widget/inventory.py
src/pvc/widget/menu.py
src/pvc/widget/motd.py
src/pvc/widget/network.py
src/pvc/widget/performance.py
src/pvc/widget/radiolist.py
src/pvc/widget/session.py
src/pvc/widget/virtualmachine.py
src/pvc/widget/vnc.py