Metadata-Version: 1.1
Name: pvc
Version: 0.3.0
Summary: Python vSphere Client with a dialog(1) interface
Home-page: https://github.com/dnaeon/pvc
Author: Marin Atanasov Nikolov
Author-email: dnaeon@gmail.com
License: BSD
Download-URL: https://github.com/dnaeon/pvc/releases
Platform: UNKNOWN
